{
  "contacts": [
    {
      "id": 1,
      "name": "John Doe",
      "email": "john@doe.com",
      "phone": "21 9 9999-0001"
    },
    {
      "nome": "Igor Campos",
      "email": "imcampos@gmail.com",
      "phone": "21 9 9999-0002",
      "id": 2
    },
    {
      "name": "igor",
      "email": "igor.crv9@gmail.com",
      "phone": "2199999999",
      "id": 6
    },
    {
      "name": "igor",
      "email": "igor.crv9@gmail.com",
      "phone": "2199999999",
      "id": 7
    },
    {
      "name": "igor2",
      "email": "igor.crv9@gmail.com",
      "phone": "2199999999",
      "id": 8
    },
    {
      "name": "igor4",
      "email": "igor.crv9@gmail.com",
      "phone": "2199999999",
      "id": 9
    },
    {
      "name": "igor4",
      "email": "igor.crv9@gmail.com",
      "phone": "2199999999",
      "id": 10
    },
    {
      "name": "igor",
      "email": "igor.crv9@gmail.com",
      "phone": "2199999999",
      "id": 11
    },
    {
      "name": "igor",
      "email": "igor.crv9@gmail.com",
      "phone": "2199999999",
      "id": 12
    },
    {
      "name": "Thiago",
      "email": "thiago@nigro.com",
      "phone": "2100000000",
      "id": 13
    },
    {
      "name": "igor5",
      "email": "igor@123.com",
      "phone": "12345678",
      "id": 14
    },
    {
      "name": "Thiago",
      "email": "igor.crv9@gmail.com",
      "phone": "2199999999",
      "id": 15
    },
    {
      "name": "igor",
      "email": "igor.crv9@gmail.com",
      "phone": "2199999999",
      "id": 16
    },
    {
      "name": "Leo",
      "email": "leo@globo.com",
      "phone": "1232135324",
      "id": 18
    },
    {
      "name": "Joao",
      "email": "thiago@nigro.com",
      "phone": "2199999999",
      "id": 20
    },
    {
      "name": "igor",
      "email": "igor.crv9@gmail.com",
      "phone": "2199999999",
      "id": 21
    }
  ]
}